feature/__init__.py
feature/_version.py
feature/base.py
feature/correlation.py
feature/kl_divergence.py
feature/linear.py
feature/selector.py
feature/statistical.py
feature/text_based.py
feature/tree_based.py
feature/utils.py
feature/variance.py
selective-1.2.0.dist-info/licenses/LICENSE.md
selective-1.2.0.dist-info/licenses/NOTICES
selective-1.2.0.dist-info/METADATA
selective-1.2.0.dist-info/WHEEL
selective-1.2.0.dist-info/top_level.txt
selective-1.2.0.dist-info/RECORD
