Metadata-Version: 2.4
Name: selective
Version: 1.2.0
Summary: feature selection library
Home-page: https://github.com/fidelity/selective
Author: FMR LLC
Project-URL: Source, https://github.com/fidelity/selective
Classifier: License :: OSI Approved :: Apache Software License
Classifier: Programming Language :: Python :: 3.8
Classifier: Operating System :: OS Independent
Requires-Python: >=3.8
License-File: LICENSE.md
License-File: NOTICES
Requires-Dist: catboost
Requires-Dist: joblib
Requires-Dist: lightgbm
Requires-Dist: numpy
Requires-Dist: mip
Requires-Dist: pandas
Requires-Dist: scikit-learn
Requires-Dist: seaborn
Requires-Dist: statsmodels
Requires-Dist: textwiser
Requires-Dist: xgboost
Dynamic: author
Dynamic: classifier
Dynamic: description
Dynamic: description-content-type
Dynamic: home-page
Dynamic: license-file
Dynamic: project-url
Dynamic: requires-dist
Dynamic: requires-python
Dynamic: summary
